can_waveshare/__init__.py
can_waveshare/bus.py
can_waveshare-0.1.0.dist-info/licenses/LICENSE
can_waveshare-0.1.0.dist-info/METADATA
can_waveshare-0.1.0.dist-info/WHEEL
can_waveshare-0.1.0.dist-info/entry_points.txt
can_waveshare-0.1.0.dist-info/top_level.txt
can_waveshare-0.1.0.dist-info/RECORD
