Metadata-Version: 2.4
Name: can-waveshare
Version: 0.1.0
Summary: python-can backend for Waveshare 2-CH-CAN-TO-ETH (13-byte TCP wire format over TCP)
Author: Klaudiusz Staniek
License-Expression: Apache-2.0
Project-URL: Homepage, https://github.com/kstaniek/python-can-waveshare-eth
Project-URL: Issues, https://github.com/kstaniek/python-can-waveshare-eth/issues
Requires-Python: >=3.10
License-File: LICENSE
Requires-Dist: python-can>=4.2
Provides-Extra: dev
Requires-Dist: pytest>=8.2; extra == "dev"
Requires-Dist: pytest-timeout>=2.3; extra == "dev"
Requires-Dist: pre-commit==4.3.0; extra == "dev"
Requires-Dist: pre-commit-hooks==6.0.0; extra == "dev"
Requires-Dist: ruff>=0.13; extra == "dev"
Requires-Dist: codespell>=2.4; extra == "dev"
Dynamic: license-file
